src/__init__.py
src/background_task.py
src/chat.py
src/convo.py
src/db.py
src/embeddings.py
src/formatting.py
src/highlight.py
src/input_reader.py
src/jsonschema.py
src/kg.py
src/logging.py
src/main.py
src/search.py
src/spin.py
src/ui_utils.py
src/viz.py
gptline-1.0.8.dist-info/LICENSE
gptline-1.0.8.dist-info/METADATA
gptline-1.0.8.dist-info/WHEEL
gptline-1.0.8.dist-info/entry_points.txt
gptline-1.0.8.dist-info/top_level.txt
gptline-1.0.8.dist-info/RECORD
