Metadata-Version: 2.1
Name: gptline
Version: 1.0.8
Summary: UNKNOWN
Home-page: UNKNOWN
License: UNKNOWN
Platform: UNKNOWN
License-File: LICENSE
Requires-Dist: openai
Requires-Dist: prompt-toolkit
Requires-Dist: simplejson
Requires-Dist: blessings
Requires-Dist: pygments
Requires-Dist: tiktoken
Requires-Dist: html2text
Requires-Dist: newspaper3k
